<?xml version="1.0" encoding="utf-8" ?>
<dwsync>
<file name="reset.css" server="O:/intra/folioport/" local="131866669700327070" remote="131866669700000000" Dst="1" />
<file name="layout.css" server="O:/intra/folioport/" local="131866680587696548" remote="131866680580000000" Dst="1" />
<file name="big.ai" server="O:/intra/folioport/" local="131867547976695040" remote="131867547970000000" Dst="1" />
<file name="h1-bg.ai" server="O:/intra/folioport/" local="131867535543230326" remote="131867535540000000" Dst="1" />
<file name="index.html" server="O:/intra/folioport/" local="131866673991927860" remote="131866673990000000" Dst="1" />
<file name="big.ai" server="O:/intra/portfolio/" local="131867547976695040" remote="131867511970000000" Dst="2" />
<file name="h1-bg.ai" server="O:/intra/portfolio/" local="131867535543230326" remote="131867499540000000" Dst="2" />
<file name="index.html" server="O:/intra/portfolio/" local="132015983686464679" remote="132015983680000000" Dst="2" />
<file name="layout.css" server="O:/intra/portfolio/" local="131866680587696548" remote="131866644580000000" Dst="2" />
<file name="reset.css" server="O:/intra/portfolio/" local="131866669700327070" remote="131866633700000000" Dst="2" />
</dwsync>